mikeracingf1/__init__.py
mikeracingf1/mikeracingf1.py
mikeracingf1-0.0.5.dist-info/LICENSE.md
mikeracingf1-0.0.5.dist-info/METADATA
mikeracingf1-0.0.5.dist-info/WHEEL
mikeracingf1-0.0.5.dist-info/top_level.txt
mikeracingf1-0.0.5.dist-info/RECORD
