Metadata-Version: 2.1
Name: mikeracingf1
Version: 0.0.5
Summary: A package for get Formula One Data
Home-page: https://github.com/micheleberardi/mikeracingf1
Author: Michele Berardi
Author-email: michymak@gmail.com
Classifier: Development Status :: 3 - Alpha
Classifier: Intended Audience :: Developers
Classifier: License :: OSI Approved :: MIT License
Classifier: Programming Language :: Python :: 3
Classifier: Programming Language :: Python :: 3.6
Classifier: Programming Language :: Python :: 3.7
Classifier: Programming Language :: Python :: 3.8
Classifier: Programming Language :: Python :: 3.9
License-File: LICENSE.md
Requires-Dist: requests
